curd2/__init__.py
curd2/errors.py
curd2/session.py
curd2/connections/__init__.py
curd2/connections/cassandra.py
curd2/connections/hbase.py
curd2/connections/mysql.py
curd2/connections/utils/__init__.py
curd2/connections/utils/cql.py
curd2/connections/utils/sql.py
tests/__init__.py
tests/conf.py
tests/operations.py
tests/test_cassandra.py
tests/test_hbase.py
tests/test_mysql.py
curd2-0.0.14.dist-info/LICENSE
curd2-0.0.14.dist-info/METADATA
curd2-0.0.14.dist-info/WHEEL
curd2-0.0.14.dist-info/top_level.txt
curd2-0.0.14.dist-info/RECORD
