Metadata-Version: 2.1
Name: curd2
Version: 0.0.14
Summary: db operations
Home-page: https://github.com/abo123456789/curd2
Author: jdxin0
Author-email: jdxin00@gmail.com
License: MIT
Keywords: db operations
Platform: UNKNOWN
Provides-Extra: cassandra
Requires-Dist: cassandra-driver (==3.11.0) ; extra == 'cassandra'
Provides-Extra: mysql
Requires-Dist: PyMySQL (==0.7.11) ; extra == 'mysql'
